baca2PackageManager/__init__.py
baca2PackageManager/broker_communication.py
baca2PackageManager/consts.py
baca2PackageManager/judge_manager.py
baca2PackageManager/manager.py
baca2PackageManager/manager_exceptions.py
baca2PackageManager/tools.py
baca2PackageManager/validators.py
baca2PackageManager/zipper.py
tests/__init__.py
tests/test_judge_manager.py
tests/test_manager.py
tests/test_tools.py
tests/test_zipper.py
baca2_package_manager-0.3.19.dist-info/LICENSE
baca2_package_manager-0.3.19.dist-info/METADATA
baca2_package_manager-0.3.19.dist-info/WHEEL
baca2_package_manager-0.3.19.dist-info/top_level.txt
baca2_package_manager-0.3.19.dist-info/RECORD
