Metadata-Version: 2.1
Name: baca2-package-manager
Version: 0.3.19
Summary: A package manager for Baca2 project
Home-page: https://github.com/BaCa2-project/BaCa2-package-manager
Author: Baca2 Team
Author-email: bartosz.deptula@student.uj.edu.pl
Classifier: Programming Language :: Python :: 3
Classifier: Development Status :: 4 - Beta
Classifier: License :: OSI Approved :: GNU General Public License v3 (GPLv3)
Requires-Python: >=3.11
License-File: LICENSE
Requires-Dist: pyyaml
Requires-Dist: pydantic
